setup.py
bin/pyfetch
bin/pyfetch_macosx_defbrowser
pyFetch/Debug.py
pyFetch/Fetch.py
pyFetch/Format.py
pyFetch/__init__.py
pyFetch/__main__.py
pyFetch/fetch.py
pyFetch/format.py
pyFetch.egg-info/PKG-INFO
pyFetch.egg-info/SOURCES.txt
pyFetch.egg-info/dependency_links.txt
pyFetch.egg-info/requires.txt
pyFetch.egg-info/top_level.txt
pyFetch/Art/__init__.py
pyFetch/Art/apple.py
pyFetch/Art/arch_big.py
pyFetch/Art/default.py
pyFetch/Art/gentoo.py
pyFetch/Art/macosx.py
pyFetch/Art/swastika.py
pyFetch/Art/swastika_no_unicode.py
pyFetch/Art/ubuntu.py
pyFetch/Art/unix_placeholder.py
pyFetch/Art/windows.py
pyFetch/Art/windows_8.py
pyFetch/Platform/Darwin.py
pyFetch/Platform/Linux.py
pyFetch/Platform/MacOSX.py
pyFetch/Platform/PlatformBase.py
pyFetch/Platform/Unix.py
pyFetch/Platform/Windows.py
pyFetch/Platform/__init__.py