Metadata-Version: 1.0
Name: pyFetch
Version: 0.2.0
Summary: Python system information tool
Home-page: https://github.com/bn0x/pyFetch
Author: bn0x and aki--aki
Author-email: 0_bn0x@hushmail.com
License: Public Domain
Keywords: screenshot system_information
Platform: UNKNOWN
Classifier: License :: CC0 1.0 Universal (CC0 1.0) Public Domain Dedication
Classifier: Programming Language :: Python
Classifier: Development Status :: 4 - Beta
